README.md
setup.py
nlpblock/__init__.py
nlpblock.egg-info/PKG-INFO
nlpblock.egg-info/SOURCES.txt
nlpblock.egg-info/dependency_links.txt
nlpblock.egg-info/requires.txt
nlpblock.egg-info/top_level.txt
nlpblock/layer/Attention.py
nlpblock/layer/AttentionOne.py
nlpblock/layer/AttentionTwo.py
nlpblock/layer/GRU.py
nlpblock/layer/LSTM.py
nlpblock/layer/MultiHeadAttention.py
nlpblock/layer/Positional_Encoding.py
nlpblock/layer/RNN.py
nlpblock/layer/ScaledDotProductAttention.py
nlpblock/layer/Transformer_EncdoerLayer.py
nlpblock/layer/Transformer_Encoder.py
nlpblock/layer/__init__.py
nlpblock/model/BiGRU_Attention.py
nlpblock/model/BiLSTM_Attention.py
nlpblock/model/BiRNN_Attention.py
nlpblock/model/GRU_Attention.py
nlpblock/model/LSTM_Attention.py
nlpblock/model/RNN_Attention.py
nlpblock/model/Seq2SeqBiGRU_Attention.py
nlpblock/model/Seq2SeqBiLSTM_Attention.py
nlpblock/model/Seq2SeqBiRNN_Attention.py
nlpblock/model/Seq2SeqGRU_Attention.py
nlpblock/model/Seq2SeqLSTM_Attention.py
nlpblock/model/Seq2SeqRNN_Attention.py
nlpblock/model/Transformer.py
nlpblock/model/__init__.py