Metadata-Version: 2.1
Name: nlpblock
Version: 0.0.1
Summary: Use All NLP models abstracted to block level with Pytorch
Home-page: https://github.com/graykode/nlpblock
Author: Tae Hwan Jung(@graykode)
Author-email: nlkey2022@gmail.com
License: MIT
Keywords: pytorch nlp nlpblock
Platform: UNKNOWN
Requires-Python: >=3.5
